{
  "colors": {
    "--Brand-Purple-Dark": {
      "cssVar": "--relay-purple-dark",
      "value": "#25254B",
      "description": "USPS Purple - Dark"
    },
    "--Brand-Purple-Base": {
      "cssVar": "--relay-purple-base",
      "value": "#333366",
      "description": "USPS Purple - Base"
    },
    "--Brand-Purple-Light": {
      "cssVar": "--relay-purple-light",
      "value": "#6464B7",
      "description": "USPS Purple - Light"
    },
    "--Brand-Purple-Lightest": {
      "cssVar": "--relay-purple-lightest",
      "value": "#B2B2F2",
      "description": "USPS Purple - Lightest"
    },
    "--Brand-Blue-Dark": {
      "cssVar": "--relay-blue-dark",
      "value": "#043359",
      "description": "USPS Blue - Dark"
    },
    "--Brand-Blue-Base": {
      "cssVar": "--relay-blue-base",
      "value": "#004B87",
      "description": "USPS Blue - Base"
    },
    "--Brand-Blue-Light": {
      "cssVar": "--relay-blue-light",
      "value": "#3573B1",
      "description": "USPS Blue - Light"
    },
    "--Brand-Blue-Lightest": {
      "cssVar": "--relay-blue-lightest",
      "value": "#6ED0F6",
      "description": "USPS Blue - Lightest"
    }
  }
}
